<?xml version="1.0" encoding="UTF-8" standalone="no"?>
<!DOCTYPE mvc PUBLIC "-//sparrow Framework//DTD mvc Configuration//EN"
        "http://www.sparrowzoo.com/dtds/mvc.dtd">
<mvc>
    <!--在bean context中定义-->
    <controller id="previewController">
        <action name="/preview.json" method="preview"/>
    </controller>

    <controller id="yamlController">
        <action name="/to-yaml.json" method="toYaml"/>
        <action name="/to-properties.json" method="toProperties"/>
    </controller>

    <controller id="commendLineFormatController">
        <action name="/commend-line-format.json" method="format"/>
    </controller>

    <controller id="wordCountController">
        <action name="/flink/word-count.json" method="wordCount"/>
    </controller>
</mvc>